{
  "averages": {
    "id": null,
    "date": "2020-04-19",
    "symbol": "AVERAGES",
    "exchange": null,
    "companyName": null,
    "price": 16.98,
    "change": 2.35081,
    "enterpriseValue": 4.2651848704E10,
    "totalCashPerShare": 1.926,
    "totalCashPerSharePercent": 11.342756183745582,
    "totalDebtEquity": 72.11,
    "trailingPE": 25.343283,
    "forwardPE": null,
    "priceToSalesTrailing12Months": 2.5896654,
    "priceBook": 2.6782334,
    "enterpriseValueRevenue": 1.524,
    "enterpriseValueEBITDA": 12.134,
    "quarterlyRevenueGrowth": null,
    "yoyQuarterlyRevenueGrowthPercent": -4.3999999999999995,
    "yoyQuarterlyEarningsGrowthPercent": 1.25,
    "earningsGrowthPercent": 1.0,
    "priceEarningGrowth": null,
    "trailingPriceEarningGrowth": 37.825795522388056,
    "week52Change": -19.754255,
    "week52Low": 14.11,
    "week52AboveLowPercent": 16.902237926972916,
    "week52High": 24.69,
    "week52BelowHighPercent": 45.40636042402827,
    "targetLowPrice": null,
    "belowTargetLowPricePercent": 24.20494699646643,
    "targetMedianPrice": null,
    "belowTargetMedianPricePercent": 42.28504122497055,
    "heldByInsiders": null,
    "heldByInstitutions": null,
    "shortToFloat": null,
    "sharesShortPrevMonthCompare": null,
    "exDividendDate": null,
    "fiveYearAvgDividendYield": null,
    "trailingAnnualDividendYield": 4.9789026,
    "periodValuationMeasures": {}
  },
  "stocks": [
    {
      "id": "5e9beb6a9797cf65d6745197",
      "date": "2020-04-19",
      "symbol": "ABBN",
      "exchange": "SIX",
      "companyName": "ABB LTD N",
      "price": 16.98,
      "change": 2.35081,
      "enterpriseValue": 4.2651848704E10,
      "totalCashPerShare": 1.926,
      "totalCashPerSharePercent": 11.342756183745582,
      "totalDebtEquity": 72.11,
      "trailingPE": 25.343283,
      "forwardPE": null,
      "priceToSalesTrailing12Months": 1.2948327,
      "priceBook": 2.6782334,
      "enterpriseValueRevenue": 1.524,
      "enterpriseValueEBITDA": 12.134,
      "quarterlyRevenueGrowth": null,
      "yoyQuarterlyRevenueGrowthPercent": -4.3999999999999995,
      "yoyQuarterlyEarningsGrowthPercent": 2.5,
      "earningsGrowthPercent": 1.0,
      "priceEarningGrowth": null,
      "trailingPriceEarningGrowth": 37.825795522388056,
      "week52Change": -19.754255,
      "week52Low": 14.11,
      "week52AboveLowPercent": 16.902237926972916,
      "week52High": 24.69,
      "week52BelowHighPercent": 45.40636042402827,
      "targetLowPrice": 21.09,
      "belowTargetLowPricePercent": 24.20494699646643,
      "targetMedianPrice": 24.16,
      "belowTargetMedianPricePercent": 42.28504122497055,
      "heldByInsiders": null,
      "heldByInstitutions": null,
      "shortToFloat": null,
      "sharesShortPrevMonthCompare": null,
      "exDividendDate": "2020-03-30",
      "fiveYearAvgDividendYield": null,
      "trailingAnnualDividendYield": 4.9789026,
      "periodValuationMeasures": {}
    }
  ]
}